blotto/__init__.py
blottopy-0.0.1.dist-info/LICENSE
blottopy-0.0.1.dist-info/METADATA
blottopy-0.0.1.dist-info/WHEEL
blottopy-0.0.1.dist-info/top_level.txt
blottopy-0.0.1.dist-info/RECORD
